youtubedlez/__main__.py
youtubedlez/sample_input.txt
youtubedlez-1.0.1.dist-info/LICENSE.txt
youtubedlez-1.0.1.dist-info/METADATA
youtubedlez-1.0.1.dist-info/WHEEL
youtubedlez-1.0.1.dist-info/entry_points.txt
youtubedlez-1.0.1.dist-info/RECORD
