Metadata-Version: 2.1
Name: youtubedlez
Version: 1.0.1
Summary: Super simple terminal interface for yt-dlp
Home-page: https://github.com/steffo99/youtubedlez
License: EUPL-1.2
Keywords: youtube,downloader,ytdlp,tui,easy
Author: Stefano Pigozzi
Author-email: me@steffo.eu
Maintainer: Stefano Pigozzi
Maintainer-email: me@steffo.eu
Requires-Python: >=3.10,<4.0
Classifier: License :: OSI Approved :: European Union Public Licence 1.2 (EUPL 1.2)
Classifier: Programming Language :: Python :: 3
Classifier: Programming Language :: Python :: 3.10
Classifier: Programming Language :: Python :: 3.11
Classifier: Programming Language :: Python :: 3.12
Requires-Dist: yt-dlp
Project-URL: Repository, https://github.com/steffo99/youtubedlez
